{"cameraMode":{"drawMode":0,"name":"Shaded","section":"Shading Mode"},"sceneLighting":true,"audioPlay":false,"sceneViewState":{"showFog":true,"showMaterialUpdate":false,"showSkybox":true,"showFlares":true,"showImageEffects":true,"showParticleSystems":true},"in2DMode":false,"pivot":{"x":10.664984703063965,"y":16.246379852294923,"z":-19.886856079101564},"rotation":{"x":0.0013737115077674389,"y":-0.9966745376586914,"z":0.08030427247285843,"w":0.017054852098226548},"size":85.10380554199219,"orthographic":false}